{
  "hotels": "სასტუმროები",
  "rooms": "ოთახები",
  "booking": "ჯავშანი",
  "quickLinks": "სწრაფი გადასვლა",
  "Contact Us": "დაგვიკავშირდით",
  "Address": "მისამართი : 14 პეკინის ქ. თბილისი",
  "Phone": "ტელ: (+995) 599-151515",
  "Email": "ელ-ფოსტა: bookinghotels.com",
  "About Us": "ჩვენს შესახებ",
  "AboutText": "მოგესალმებით Booking.com-ზე,  ჩვენი პლატფორმა გთავაზობთ ბრწყინვალე რეზერვაციის გამოცდილებას, მრავალფეროვანი საცხოვრებელი ადგილის არჩევას, რომელიც შეესაბამება ყველა საჭიროებას და ბიუჯეტს. Booking.com-ზე, ჩვენ ერთგულნი ვართ უჩვეულო მომსახურების მიწოდებაში, რაც უზრუნველყოფს თქვენი ყოფნის კომფორტსა და სიამოვნებას. ჩვენ შეგვიძლია გავხადოთ თქვენი მომდევნო მოგზაურობა დაუვიწყარი.",
  "Follow Us":"ასევე გვიპოვეთ",
  "Price Per Night":"ერთი ღამის ფასი",
  "Room Reservation":"ოთახის დაჯავშნა",
  "Customer Name":"სახელი და გვარი",
  "Customer Phone":"ტელეფონი",
  "Check-in Date":"რიცხვიდან",
  "Check-out Date":"რიცხვამდე",
  "Reserve":"დაჯავშნა",
  "Total Price:":"სრული ღირებულება",
  "See More":"სრულად",
  "Overview":"მიმოხილვა",
  "LatestNews":"სიახლეები",
  "NewHotelOpenings":"ახალი სასტუმროები თბილისში",
  "Discoverhotels":"აღმოაჩინეთ უახლესი სასტუმროს გახსნა მთავარ ადგილებში.",
  "Traveltips":"მოგზაურობის რჩევები",
  "tips":"მიიღეთ საუკეთესო სამოგზაურო რჩევები თქვენი შემდეგი შვებულებისთვის.",
  "promotions":"სპეციალური შეთავაზებები",
  "Hotelgallery":"სასტუროები",
  "Seasonalhighlights":"სეზონური მაჩვენებლები",
  "comments":"კომენტარები",
  "higlight-text":"შეიტყვეთ სეზონური მოვლენებისა და აქტივობების შესახებ, რომლითაც ისიამოვნეთ თქვენი მოგზაურობის დროს.",
  "promotion-text":"ისარგებლეთ ჩვენი ექსკლუზიური გარიგებებით და დაზოგეთ თქვენი შემდეგი ჯავშანი",
  "OverviewText":"აღმოაჩინეთ საუკეთესო სტუმართმოყვარეობის გამოცდილება ჩვენს გულდასმით შერჩეულ საუკეთესო სასტუმროების კოლექციაში მთელს მსოფლიოში. ჩვენი პორტფოლიოს თითოეული ქონება ცნობილია თავისი განსაკუთრებული მომსახურებით, მდიდრული კეთილმოწყობითა და დეტალებისადმი ყურადღების მიღებით, რაც უზრუნველყოფს, რომ თქვენი ყოფნის ყველა ასპექტი არაჩვეულებრივია. საქმიანი თუ დასასვენებლად მოგზაურობთ, ჩვენი სასტუმროები მზად არიან უზრუნველყონ კომფორტისა და დახვეწილობის განუმეორებელი დონე."

}
